find_job_titles/__init__.py
find_job_titles/data/titles_combined.txt.gz
find_job_titles-0.7.0.dist-info/DESCRIPTION.rst
find_job_titles-0.7.0.dist-info/METADATA
find_job_titles-0.7.0.dist-info/RECORD
find_job_titles-0.7.0.dist-info/WHEEL
find_job_titles-0.7.0.dist-info/metadata.json
find_job_titles-0.7.0.dist-info/top_level.txt
