Metadata-Version: 1.1
Name: find-job-titles
Version: 0.7.0
Summary: Fast extraction of job titles from strings
Home-page: https://github.com/fluquid/find_job_titles
Author: Johannes Ahlmann
Author-email: johannes@fluquid.com
License: MIT
Keywords: extract,job titles
Platform: UNKNOWN
Classifier: Development Status :: 2 - Pre-Alpha
Classifier: Intended Audience :: Developers
Classifier: License :: OSI Approved :: MIT License
Classifier: Natural Language :: English
Classifier: Programming Language :: Python :: 2
Classifier: Programming Language :: Python :: 2.7
Classifier: Programming Language :: Python :: 3
Classifier: Programming Language :: Python :: 3.4
Classifier: Programming Language :: Python :: 3.5
